cgmm/__init__.py
cgmm/base.py
cgmm/conditioner.py
cgmm/discriminative.py
cgmm/moe.py
cgmm/regressor.py
cgmm-0.4.0.dist-info/METADATA
cgmm-0.4.0.dist-info/WHEEL
cgmm-0.4.0.dist-info/licenses/LICENSE
cgmm-0.4.0.dist-info/RECORD
