Metadata-Version: 2.4
Name: cgmm
Version: 0.4.0
Summary: Conditional Gaussian Mixture Models compatible with scikit-learn
License: BSD-3-Clause
License-File: LICENSE
Keywords: gaussian mixture,scikit-learn,conditional
Author: Thijs van den Berg
Author-email: thijs@sitmo.com
Requires-Python: >=3.9,<3.13
Classifier: License :: OSI Approved :: BSD License
Classifier: Programming Language :: Python :: 3
Classifier: Programming Language :: Python :: 3.9
Classifier: Programming Language :: Python :: 3.10
Classifier: Programming Language :: Python :: 3.11
Classifier: Programming Language :: Python :: 3.12
Provides-Extra: docs
Requires-Dist: furo (>=2024.8) ; extra == "docs"
Requires-Dist: matplotlib (>=3.8) ; extra == "docs"
Requires-Dist: myst-nb (>=1.1) ; extra == "docs"
Requires-Dist: numpy
Requires-Dist: pandas (>=2.3,<3.0) ; extra == "docs"
Requires-Dist: scikit-learn
Requires-Dist: scipy
Requires-Dist: sphinx (>=7) ; extra == "docs"
Requires-Dist: sphinx-copybutton (>=0.5.2) ; extra == "docs"
Project-URL: Homepage, https://github.com/sitmo/cgmm
Project-URL: Repository, https://github.com/sitmo/cgmm
